{
  "minVersion": "0.8",
  "compatibilityLevel": "JAVA_8",
  "mixinPriority": 1,
  "package": "io.github.zekerzhayard.optiforge.asm.mixins",
  "client": [
    "net.minecraft.client.renderer.MixinWorldRenderer",
    "net.minecraft.client.renderer.entity.MixinItemFrameRenderer",
    "net.minecraft.client.renderer.entity.MixinItemRenderer",
    "net.minecraft.client.renderer.entity.MixinLivingRenderer",
    "net.minecraft.client.renderer.entity.layers.MixinBipedArmorLayer",
    "net.minecraft.client.renderer.entity.layers.MixinElytraLayer",
    "net.minecraft.client.renderer.model.MixinFaceBakery",
    "net.minecraft.client.renderer.model.MixinModelBakery",
    "net.minecraft.client.renderer.texture.MixinAtlasTexture",
    "net.minecraft.client.renderer.texture.MixinStitcher",
    "net.minecraft.network.datasync.MixinEntityDataManager"
  ],
  "plugin": "io.github.zekerzhayard.optiforge.asm.MixinConfigPlugin",
  "injectors": {
    "maxShiftBy": 2
  }
}